Metadata-Version: 2.1
Name: statistics-quantile
Version: 0.0.1
Summary: quantile in Python
Home-page: https://github.com/mahdi-zarepour/quantile
Author: Mahdi-Zarepour
Author-email: mahdizarepour40@gmail.com
License: MIT
Platform: UNKNOWN
Requires-Python: >=3.8
License-File: LICENSE
